{
  "ativos": [
    {
      "nome": "TESTEa",
      "modelo": "asas",
      "id": 4
    }
  ],
  "usuarios": [
    {
      "id": 1,
      "email": "joao@example.com",
      "nome": "Jo達o",
      "time": "dev",
      "local": "sjc"
    },
    {
      "id": 2,
      "email": "joao@example.com",
      "nome": "Jo達o",
      "time": "dev",
      "local": "sjc"
    },
    {
      "id": 3,
      "email": "joao@example.com",
      "nome": "Jo達o",
      "time": "dev",
      "local": "sjc"
    },
    {
      "id": 4,
      "email": "joao@example.com",
      "nome": "Jo達o",
      "time": "dev",
      "local": "sjc"
    }
  ]
}